neosphere/__init__.py
neosphere/agent.py
neosphere/client_api.py
neosphere/contacts_handler.py
neosphere/media_handler.py
neosphere/extra_tools/__init__.py
neosphere/extra_tools/message_logger.py
neosphere/extra_tools/text_context_gather.py
neosphere/tests/__init__.py
neosphere/tests/test_message_logger.py
neosphere-0.5.3.dist-info/licenses/LICENSE
neosphere-0.5.3.dist-info/METADATA
neosphere-0.5.3.dist-info/WHEEL
neosphere-0.5.3.dist-info/top_level.txt
neosphere-0.5.3.dist-info/RECORD
