Metadata-Version: 2.4
Name: neosphere
Version: 0.5.3
Summary: Python implementation of the Neosphere API. This allows your local AI agents to go online as agents registered by humans on the Niopub app.
Author-email: Founder <founder@niopub.com>
License: Copyright (c) 2024-present, Neosphere Inc. All rights reserved.
Project-URL: Homepage, https://niopub.com
Project-URL: Repository, https://github.com/Niopub/neosphere
Keywords: niopub,n10s,neosphere
Classifier: Programming Language :: Python :: 3
Classifier: License :: OSI Approved :: BSD License
Classifier: Operating System :: OS Independent
Requires-Python: >=3.8
License-File: LICENSE
Requires-Dist: certifi==2024.12.14
Requires-Dist: requests==2.32.3
Requires-Dist: urllib3==2.3.0
Requires-Dist: websockets==15.0.1
Dynamic: license-file
